massaction/__init__.py
massaction/constraint.py
massaction/model.py
massaction/reaction.py
massaction/species.py
massaction-0.2.1.dist-info/LICENSE
massaction-0.2.1.dist-info/METADATA
massaction-0.2.1.dist-info/WHEEL
massaction-0.2.1.dist-info/top_level.txt
massaction-0.2.1.dist-info/RECORD
