Metadata-Version: 2.1
Name: massaction
Version: 0.2.1
Summary: Numerical solution of mass-action laws
Author-email: "Adrian L. Usler" <adrian.usler@rwth-aachen.de>
License: MIT License
Project-URL: Homepage, https://github.com/adrianusler/massaction
Project-URL: Issues, https://github.com/adrianusler/massaction/issues
Classifier: Programming Language :: Python :: 3
Classifier: License :: OSI Approved :: MIT License
Classifier: Operating System :: OS Independent
Requires-Python: ~=3.8
License-File: LICENSE
Requires-Dist: numpy<3.0,>=1.22
Requires-Dist: scipy>=1.7.0
Provides-Extra: tests
Requires-Dist: pytest>=7; extra == "tests"
Requires-Dist: pytest-cov>=5; extra == "tests"
